{
  "pred_topN_logisticRegressionModel.json": {
    "dstar": {
      "top1": 8,
      "top2": 8,
      "top3": 9,
      "top4": 12,
      "top5": 13,
      "top10": 14,
      "top15": 14,
      "top20": 14
    },
    "ochiai": {
      "top1": 8,
      "top2": 8,
      "top3": 11,
      "top4": 12,
      "top5": 13,
      "top10": 14,
      "top15": 14,
      "top20": 14
    },
    "gp13": {
      "top1": 8,
      "top2": 8,
      "top3": 9,
      "top4": 12,
      "top5": 13,
      "top10": 14,
      "top15": 14,
      "top20": 14
    },
    "op2": {
      "top1": 8,
      "top2": 8,
      "top3": 9,
      "top4": 12,
      "top5": 13,
      "top10": 14,
      "top15": 14,
      "top20": 14
    },
    "jaccard": {
      "top1": 8,
      "top2": 8,
      "top3": 9,
      "top4": 12,
      "top5": 13,
      "top10": 14,
      "top15": 14,
      "top20": 14
    },
    "russell": {
      "top1": 8,
      "top2": 8,
      "top3": 9,
      "top4": 13,
      "top5": 14,
      "top10": 14,
      "top15": 14,
      "top20": 14
    },
    "turantula": {
      "top1": 11,
      "top2": 11,
      "top3": 11,
      "top4": 12,
      "top5": 13,
      "top10": 14,
      "top15": 14,
      "top20": 14
    },
    "naish1": {
      "top1": 5,
      "top2": 5,
      "top3": 5,
      "top4": 5,
      "top5": 9,
      "top10": 10,
      "top15": 11,
      "top20": 11
    },
    "binary": {
      "top1": 14,
      "top2": 14,
      "top3": 14,
      "top4": 14,
      "top5": 14,
      "top10": 14,
      "top15": 14,
      "top20": 14
    },
    "crosstab": {
      "top1": 9,
      "top2": 9,
      "top3": 12,
      "top4": 12,
      "top5": 13,
      "top10": 14,
      "top15": 14,
      "top20": 14
    }
  },
  "pred_topN_randomForestModel.json": {
    "dstar": {
      "top1": 8,
      "top2": 8,
      "top3": 9,
      "top4": 11,
      "top5": 12,
      "top10": 13,
      "top15": 14,
      "top20": 14
    },
    "ochiai": {
      "top1": 7,
      "top2": 7,
      "top3": 9,
      "top4": 11,
      "top5": 12,
      "top10": 13,
      "top15": 14,
      "top20": 14
    },
    "gp13": {
      "top1": 7,
      "top2": 7,
      "top3": 8,
      "top4": 11,
      "top5": 11,
      "top10": 13,
      "top15": 14,
      "top20": 14
    },
    "op2": {
      "top1": 7,
      "top2": 7,
      "top3": 8,
      "top4": 11,
      "top5": 11,
      "top10": 13,
      "top15": 14,
      "top20": 14
    },
    "jaccard": {
      "top1": 7,
      "top2": 7,
      "top3": 9,
      "top4": 11,
      "top5": 12,
      "top10": 14,
      "top15": 14,
      "top20": 14
    },
    "russell": {
      "top1": 11,
      "top2": 11,
      "top3": 11,
      "top4": 11,
      "top5": 11,
      "top10": 13,
      "top15": 14,
      "top20": 14
    },
    "turantula": {
      "top1": 10,
      "top2": 10,
      "top3": 10,
      "top4": 12,
      "top5": 12,
      "top10": 14,
      "top15": 14,
      "top20": 14
    },
    "naish1": {
      "top1": 5,
      "top2": 5,
      "top3": 5,
      "top4": 7,
      "top5": 9,
      "top10": 11,
      "top15": 11,
      "top20": 11
    },
    "binary": {
      "top1": 14,
      "top2": 14,
      "top3": 14,
      "top4": 14,
      "top5": 14,
      "top10": 14,
      "top15": 14,
      "top20": 14
    },
    "crosstab": {
      "top1": 8,
      "top2": 8,
      "top3": 10,
      "top4": 11,
      "top5": 12,
      "top10": 14,
      "top15": 14,
      "top20": 14
    }
  },
  "pred_topN_naiveBayesModel.json": {
    "dstar": {
      "top1": 8,
      "top2": 8,
      "top3": 8,
      "top4": 11,
      "top5": 12,
      "top10": 13,
      "top15": 13,
      "top20": 13
    },
    "ochiai": {
      "top1": 8,
      "top2": 8,
      "top3": 10,
      "top4": 11,
      "top5": 12,
      "top10": 13,
      "top15": 13,
      "top20": 13
    },
    "gp13": {
      "top1": 8,
      "top2": 8,
      "top3": 8,
      "top4": 11,
      "top5": 12,
      "top10": 13,
      "top15": 13,
      "top20": 13
    },
    "op2": {
      "top1": 8,
      "top2": 8,
      "top3": 8,
      "top4": 11,
      "top5": 12,
      "top10": 13,
      "top15": 13,
      "top20": 13
    },
    "jaccard": {
      "top1": 8,
      "top2": 8,
      "top3": 8,
      "top4": 11,
      "top5": 12,
      "top10": 13,
      "top15": 13,
      "top20": 13
    },
    "russell": {
      "top1": 9,
      "top2": 9,
      "top3": 9,
      "top4": 13,
      "top5": 14,
      "top10": 14,
      "top15": 14,
      "top20": 14
    },
    "turantula": {
      "top1": 10,
      "top2": 10,
      "top3": 10,
      "top4": 11,
      "top5": 12,
      "top10": 13,
      "top15": 13,
      "top20": 13
    },
    "naish1": {
      "top1": 7,
      "top2": 7,
      "top3": 7,
      "top4": 7,
      "top5": 11,
      "top10": 12,
      "top15": 13,
      "top20": 13
    },
    "binary": {
      "top1": 11,
      "top2": 11,
      "top3": 11,
      "top4": 11,
      "top5": 11,
      "top10": 13,
      "top15": 13,
      "top20": 13
    },
    "crosstab": {
      "top1": 8,
      "top2": 8,
      "top3": 10,
      "top4": 10,
      "top5": 11,
      "top10": 12,
      "top15": 12,
      "top20": 12
    }
  },
  "pred_topN_pmt.json": {
    "dstar": {
      "top1": 6,
      "top2": 6,
      "top3": 9,
      "top4": 10,
      "top5": 14,
      "top10": 14,
      "top15": 14,
      "top20": 14
    },
    "ochiai": {
      "top1": 6,
      "top2": 6,
      "top3": 9,
      "top4": 10,
      "top5": 14,
      "top10": 14,
      "top15": 14,
      "top20": 14
    },
    "gp13": {
      "top1": 6,
      "top2": 6,
      "top3": 9,
      "top4": 10,
      "top5": 14,
      "top10": 14,
      "top15": 14,
      "top20": 14
    },
    "op2": {
      "top1": 6,
      "top2": 6,
      "top3": 9,
      "top4": 10,
      "top5": 14,
      "top10": 14,
      "top15": 14,
      "top20": 14
    },
    "jaccard": {
      "top1": 6,
      "top2": 6,
      "top3": 9,
      "top4": 10,
      "top5": 14,
      "top10": 14,
      "top15": 14,
      "top20": 14
    },
    "russell": {
      "top1": 7,
      "top2": 7,
      "top3": 10,
      "top4": 11,
      "top5": 14,
      "top10": 14,
      "top15": 14,
      "top20": 14
    },
    "turantula": {
      "top1": 10,
      "top2": 10,
      "top3": 11,
      "top4": 13,
      "top5": 14,
      "top10": 14,
      "top15": 14,
      "top20": 14
    },
    "naish1": {
      "top1": 5,
      "top2": 5,
      "top3": 5,
      "top4": 5,
      "top5": 9,
      "top10": 10,
      "top15": 11,
      "top20": 11
    },
    "binary": {
      "top1": 14,
      "top2": 14,
      "top3": 14,
      "top4": 14,
      "top5": 14,
      "top10": 14,
      "top15": 14,
      "top20": 14
    },
    "crosstab": {
      "top1": 8,
      "top2": 8,
      "top3": 11,
      "top4": 11,
      "top5": 14,
      "top10": 14,
      "top15": 14,
      "top20": 14
    }
  },
  "pred_topN_pmbfl.json": {
    "ochiai": {
      "top1": 7,
      "top2": 9,
      "top3": 13,
      "top4": 13,
      "top5": 13,
      "top10": 14,
      "top15": 14,
      "top20": 14
    }
  },
  "pred_topN_pmbfl2.json": {
    "ochiai": {
      "top1": 10,
      "top2": 10,
      "top3": 10,
      "top4": 13,
      "top5": 13,
      "top10": 14,
      "top15": 14,
      "top20": 14
    }
  },
  "pred_topN_pmbfl_2.json": {
    "dstar": {
      "top1": 7,
      "top2": 8,
      "top3": 8,
      "top4": 10,
      "top5": 10,
      "top10": 14,
      "top15": 14,
      "top20": 14
    },
    "ochiai": {
      "top1": 4,
      "top2": 6,
      "top3": 11,
      "top4": 12,
      "top5": 12,
      "top10": 14,
      "top15": 14,
      "top20": 14
    },
    "gp13": {
      "top1": 4,
      "top2": 5,
      "top3": 9,
      "top4": 12,
      "top5": 12,
      "top10": 14,
      "top15": 14,
      "top20": 14
    },
    "op2": {
      "top1": 4,
      "top2": 6,
      "top3": 9,
      "top4": 12,
      "top5": 12,
      "top10": 14,
      "top15": 14,
      "top20": 14
    },
    "jaccard": {
      "top1": 4,
      "top2": 6,
      "top3": 11,
      "top4": 12,
      "top5": 13,
      "top10": 14,
      "top15": 14,
      "top20": 14
    },
    "russell": {
      "top1": 6,
      "top2": 8,
      "top3": 11,
      "top4": 13,
      "top5": 13,
      "top10": 14,
      "top15": 14,
      "top20": 14
    },
    "turantula": {
      "top1": 6,
      "top2": 8,
      "top3": 11,
      "top4": 12,
      "top5": 13,
      "top10": 14,
      "top15": 14,
      "top20": 14
    },
    "naish1": {
      "top1": 4,
      "top2": 8,
      "top3": 11,
      "top4": 12,
      "top5": 12,
      "top10": 14,
      "top15": 14,
      "top20": 14
    },
    "binary": {
      "top1": 14,
      "top2": 14,
      "top3": 14,
      "top4": 14,
      "top5": 14,
      "top10": 14,
      "top15": 14,
      "top20": 14
    },
    "crosstab": {
      "top1": 8,
      "top2": 10,
      "top3": 12,
      "top4": 14,
      "top5": 14,
      "top10": 14,
      "top15": 14,
      "top20": 14
    }
  },
  "pred_topN_pmbfl_1.json": {
    "dstar": {
      "top1": 7,
      "top2": 7,
      "top3": 9,
      "top4": 11,
      "top5": 11,
      "top10": 14,
      "top15": 14,
      "top20": 14
    },
    "ochiai": {
      "top1": 6,
      "top2": 10,
      "top3": 11,
      "top4": 12,
      "top5": 13,
      "top10": 14,
      "top15": 14,
      "top20": 14
    },
    "gp13": {
      "top1": 4,
      "top2": 6,
      "top3": 12,
      "top4": 12,
      "top5": 14,
      "top10": 14,
      "top15": 14,
      "top20": 14
    },
    "op2": {
      "top1": 5,
      "top2": 6,
      "top3": 12,
      "top4": 12,
      "top5": 14,
      "top10": 14,
      "top15": 14,
      "top20": 14
    },
    "jaccard": {
      "top1": 6,
      "top2": 9,
      "top3": 11,
      "top4": 12,
      "top5": 13,
      "top10": 14,
      "top15": 14,
      "top20": 14
    },
    "russell": {
      "top1": 7,
      "top2": 7,
      "top3": 11,
      "top4": 11,
      "top5": 12,
      "top10": 14,
      "top15": 14,
      "top20": 14
    },
    "turantula": {
      "top1": 8,
      "top2": 11,
      "top3": 13,
      "top4": 13,
      "top5": 14,
      "top10": 14,
      "top15": 14,
      "top20": 14
    },
    "naish1": {
      "top1": 4,
      "top2": 9,
      "top3": 11,
      "top4": 11,
      "top5": 12,
      "top10": 14,
      "top15": 14,
      "top20": 14
    },
    "binary": {
      "top1": 14,
      "top2": 14,
      "top3": 14,
      "top4": 14,
      "top5": 14,
      "top10": 14,
      "top15": 14,
      "top20": 14
    },
    "crosstab": {
      "top1": 7,
      "top2": 11,
      "top3": 12,
      "top4": 13,
      "top5": 13,
      "top10": 14,
      "top15": 14,
      "top20": 14
    }
  },
  "pred_topN_pmbfl_3.json": {
    "dstar": {
      "top1": 7,
      "top2": 8,
      "top3": 9,
      "top4": 9,
      "top5": 9,
      "top10": 14,
      "top15": 14,
      "top20": 14
    },
    "ochiai": {
      "top1": 5,
      "top2": 7,
      "top3": 11,
      "top4": 12,
      "top5": 12,
      "top10": 14,
      "top15": 14,
      "top20": 14
    },
    "gp13": {
      "top1": 5,
      "top2": 7,
      "top3": 10,
      "top4": 11,
      "top5": 12,
      "top10": 14,
      "top15": 14,
      "top20": 14
    },
    "op2": {
      "top1": 5,
      "top2": 7,
      "top3": 9,
      "top4": 10,
      "top5": 10,
      "top10": 14,
      "top15": 14,
      "top20": 14
    },
    "jaccard": {
      "top1": 5,
      "top2": 7,
      "top3": 10,
      "top4": 11,
      "top5": 12,
      "top10": 14,
      "top15": 14,
      "top20": 14
    },
    "russell": {
      "top1": 7,
      "top2": 9,
      "top3": 11,
      "top4": 11,
      "top5": 11,
      "top10": 14,
      "top15": 14,
      "top20": 14
    },
    "turantula": {
      "top1": 8,
      "top2": 10,
      "top3": 13,
      "top4": 13,
      "top5": 13,
      "top10": 14,
      "top15": 14,
      "top20": 14
    },
    "naish1": {
      "top1": 4,
      "top2": 8,
      "top3": 10,
      "top4": 10,
      "top5": 11,
      "top10": 14,
      "top15": 14,
      "top20": 14
    },
    "binary": {
      "top1": 14,
      "top2": 14,
      "top3": 14,
      "top4": 14,
      "top5": 14,
      "top10": 14,
      "top15": 14,
      "top20": 14
    },
    "crosstab": {
      "top1": 7,
      "top2": 11,
      "top3": 12,
      "top4": 12,
      "top5": 13,
      "top10": 14,
      "top15": 14,
      "top20": 14
    }
  },
  "pred_topN_pmbfl_4.json": {
    "dstar": {
      "top1": 7,
      "top2": 7,
      "top3": 9,
      "top4": 11,
      "top5": 11,
      "top10": 14,
      "top15": 14,
      "top20": 14
    },
    "ochiai": {
      "top1": 7,
      "top2": 8,
      "top3": 13,
      "top4": 13,
      "top5": 14,
      "top10": 14,
      "top15": 14,
      "top20": 14
    },
    "gp13": {
      "top1": 4,
      "top2": 6,
      "top3": 13,
      "top4": 13,
      "top5": 13,
      "top10": 14,
      "top15": 14,
      "top20": 14
    },
    "op2": {
      "top1": 5,
      "top2": 7,
      "top3": 13,
      "top4": 13,
      "top5": 13,
      "top10": 14,
      "top15": 14,
      "top20": 14
    },
    "jaccard": {
      "top1": 7,
      "top2": 8,
      "top3": 12,
      "top4": 13,
      "top5": 13,
      "top10": 14,
      "top15": 14,
      "top20": 14
    },
    "russell": {
      "top1": 7,
      "top2": 7,
      "top3": 12,
      "top4": 12,
      "top5": 12,
      "top10": 14,
      "top15": 14,
      "top20": 14
    },
    "turantula": {
      "top1": 8,
      "top2": 10,
      "top3": 14,
      "top4": 14,
      "top5": 14,
      "top10": 14,
      "top15": 14,
      "top20": 14
    },
    "naish1": {
      "top1": 4,
      "top2": 9,
      "top3": 11,
      "top4": 12,
      "top5": 12,
      "top10": 14,
      "top15": 14,
      "top20": 14
    },
    "binary": {
      "top1": 14,
      "top2": 14,
      "top3": 14,
      "top4": 14,
      "top5": 14,
      "top10": 14,
      "top15": 14,
      "top20": 14
    },
    "crosstab": {
      "top1": 8,
      "top2": 11,
      "top3": 11,
      "top4": 13,
      "top5": 13,
      "top10": 14,
      "top15": 14,
      "top20": 14
    }
  },
  "pred_topN_pmbfl_5.json": {
    "dstar": {
      "top1": 7,
      "top2": 8,
      "top3": 8,
      "top4": 11,
      "top5": 11,
      "top10": 14,
      "top15": 14,
      "top20": 14
    },
    "ochiai": {
      "top1": 6,
      "top2": 8,
      "top3": 12,
      "top4": 12,
      "top5": 12,
      "top10": 14,
      "top15": 14,
      "top20": 14
    },
    "gp13": {
      "top1": 4,
      "top2": 7,
      "top3": 11,
      "top4": 13,
      "top5": 13,
      "top10": 14,
      "top15": 14,
      "top20": 14
    },
    "op2": {
      "top1": 5,
      "top2": 7,
      "top3": 11,
      "top4": 13,
      "top5": 13,
      "top10": 14,
      "top15": 14,
      "top20": 14
    },
    "jaccard": {
      "top1": 6,
      "top2": 7,
      "top3": 11,
      "top4": 12,
      "top5": 12,
      "top10": 14,
      "top15": 14,
      "top20": 14
    },
    "russell": {
      "top1": 7,
      "top2": 9,
      "top3": 11,
      "top4": 13,
      "top5": 13,
      "top10": 14,
      "top15": 14,
      "top20": 14
    },
    "turantula": {
      "top1": 7,
      "top2": 9,
      "top3": 13,
      "top4": 13,
      "top5": 14,
      "top10": 14,
      "top15": 14,
      "top20": 14
    },
    "naish1": {
      "top1": 4,
      "top2": 8,
      "top3": 12,
      "top4": 12,
      "top5": 13,
      "top10": 14,
      "top15": 14,
      "top20": 14
    },
    "binary": {
      "top1": 14,
      "top2": 14,
      "top3": 14,
      "top4": 14,
      "top5": 14,
      "top10": 14,
      "top15": 14,
      "top20": 14
    },
    "crosstab": {
      "top1": 8,
      "top2": 10,
      "top3": 12,
      "top4": 13,
      "top5": 14,
      "top10": 14,
      "top15": 14,
      "top20": 14
    }
  },
  "pred_topN_randomForestModel_20.json": {
    "dstar": {
      "top1": 7,
      "top2": 8,
      "top3": 8,
      "top4": 9,
      "top5": 11,
      "top10": 13,
      "top15": 13,
      "top20": 14
    },
    "ochiai": {
      "top1": 7,
      "top2": 8,
      "top3": 10,
      "top4": 10,
      "top5": 11,
      "top10": 13,
      "top15": 13,
      "top20": 14
    },
    "gp13": {
      "top1": 7,
      "top2": 7,
      "top3": 8,
      "top4": 8,
      "top5": 10,
      "top10": 13,
      "top15": 13,
      "top20": 14
    },
    "op2": {
      "top1": 7,
      "top2": 7,
      "top3": 8,
      "top4": 8,
      "top5": 10,
      "top10": 13,
      "top15": 13,
      "top20": 14
    },
    "jaccard": {
      "top1": 7,
      "top2": 8,
      "top3": 10,
      "top4": 10,
      "top5": 11,
      "top10": 13,
      "top15": 13,
      "top20": 14
    },
    "russell": {
      "top1": 8,
      "top2": 9,
      "top3": 10,
      "top4": 11,
      "top5": 11,
      "top10": 14,
      "top15": 14,
      "top20": 14
    },
    "turantula": {
      "top1": 6,
      "top2": 9,
      "top3": 10,
      "top4": 10,
      "top5": 11,
      "top10": 13,
      "top15": 13,
      "top20": 14
    },
    "naish1": {
      "top1": 9,
      "top2": 9,
      "top3": 9,
      "top4": 10,
      "top5": 10,
      "top10": 13,
      "top15": 13,
      "top20": 14
    },
    "binary": {
      "top1": 7,
      "top2": 7,
      "top3": 12,
      "top4": 12,
      "top5": 12,
      "top10": 12,
      "top15": 13,
      "top20": 13
    },
    "crosstab": {
      "top1": 10,
      "top2": 10,
      "top3": 12,
      "top4": 12,
      "top5": 13,
      "top10": 14,
      "top15": 14,
      "top20": 14
    }
  },
  "pred_topN_randomForestModel_30.json": {
    "dstar": {
      "top1": 7,
      "top2": 7,
      "top3": 9,
      "top4": 10,
      "top5": 10,
      "top10": 13,
      "top15": 14,
      "top20": 14
    },
    "ochiai": {
      "top1": 5,
      "top2": 8,
      "top3": 11,
      "top4": 12,
      "top5": 13,
      "top10": 14,
      "top15": 14,
      "top20": 14
    },
    "gp13": {
      "top1": 5,
      "top2": 7,
      "top3": 11,
      "top4": 11,
      "top5": 11,
      "top10": 14,
      "top15": 14,
      "top20": 14
    },
    "op2": {
      "top1": 5,
      "top2": 7,
      "top3": 11,
      "top4": 11,
      "top5": 11,
      "top10": 14,
      "top15": 14,
      "top20": 14
    },
    "jaccard": {
      "top1": 5,
      "top2": 6,
      "top3": 9,
      "top4": 12,
      "top5": 13,
      "top10": 14,
      "top15": 14,
      "top20": 14
    },
    "russell": {
      "top1": 7,
      "top2": 7,
      "top3": 11,
      "top4": 11,
      "top5": 11,
      "top10": 14,
      "top15": 14,
      "top20": 14
    },
    "turantula": {
      "top1": 6,
      "top2": 9,
      "top3": 12,
      "top4": 12,
      "top5": 13,
      "top10": 14,
      "top15": 14,
      "top20": 14
    },
    "naish1": {
      "top1": 4,
      "top2": 10,
      "top3": 11,
      "top4": 11,
      "top5": 11,
      "top10": 13,
      "top15": 13,
      "top20": 13
    },
    "binary": {
      "top1": 14,
      "top2": 14,
      "top3": 14,
      "top4": 14,
      "top5": 14,
      "top10": 14,
      "top15": 14,
      "top20": 14
    },
    "crosstab": {
      "top1": 7,
      "top2": 11,
      "top3": 13,
      "top4": 14,
      "top5": 14,
      "top10": 14,
      "top15": 14,
      "top20": 14
    }
  },
  "pred_topN_randomForestModel_40.json": {
    "dstar": {
      "top1": 7,
      "top2": 8,
      "top3": 8,
      "top4": 9,
      "top5": 11,
      "top10": 14,
      "top15": 14,
      "top20": 14
    },
    "ochiai": {
      "top1": 4,
      "top2": 7,
      "top3": 10,
      "top4": 11,
      "top5": 11,
      "top10": 14,
      "top15": 14,
      "top20": 14
    },
    "gp13": {
      "top1": 5,
      "top2": 7,
      "top3": 9,
      "top4": 10,
      "top5": 10,
      "top10": 14,
      "top15": 14,
      "top20": 14
    },
    "op2": {
      "top1": 6,
      "top2": 7,
      "top3": 8,
      "top4": 9,
      "top5": 10,
      "top10": 14,
      "top15": 14,
      "top20": 14
    },
    "jaccard": {
      "top1": 3,
      "top2": 6,
      "top3": 9,
      "top4": 11,
      "top5": 13,
      "top10": 14,
      "top15": 14,
      "top20": 14
    },
    "russell": {
      "top1": 6,
      "top2": 7,
      "top3": 11,
      "top4": 11,
      "top5": 11,
      "top10": 14,
      "top15": 14,
      "top20": 14
    },
    "turantula": {
      "top1": 7,
      "top2": 9,
      "top3": 11,
      "top4": 11,
      "top5": 11,
      "top10": 14,
      "top15": 14,
      "top20": 14
    },
    "naish1": {
      "top1": 4,
      "top2": 9,
      "top3": 9,
      "top4": 9,
      "top5": 10,
      "top10": 13,
      "top15": 13,
      "top20": 13
    },
    "binary": {
      "top1": 14,
      "top2": 14,
      "top3": 14,
      "top4": 14,
      "top5": 14,
      "top10": 14,
      "top15": 14,
      "top20": 14
    },
    "crosstab": {
      "top1": 7,
      "top2": 9,
      "top3": 12,
      "top4": 14,
      "top5": 14,
      "top10": 14,
      "top15": 14,
      "top20": 14
    }
  },
  "pred_topN_randomForestModel_50.json": {
    "dstar": {
      "top1": 7,
      "top2": 7,
      "top3": 9,
      "top4": 9,
      "top5": 10,
      "top10": 14,
      "top15": 14,
      "top20": 14
    },
    "ochiai": {
      "top1": 5,
      "top2": 8,
      "top3": 10,
      "top4": 11,
      "top5": 12,
      "top10": 14,
      "top15": 14,
      "top20": 14
    },
    "gp13": {
      "top1": 4,
      "top2": 7,
      "top3": 10,
      "top4": 10,
      "top5": 10,
      "top10": 14,
      "top15": 14,
      "top20": 14
    },
    "op2": {
      "top1": 4,
      "top2": 7,
      "top3": 10,
      "top4": 10,
      "top5": 10,
      "top10": 14,
      "top15": 14,
      "top20": 14
    },
    "jaccard": {
      "top1": 5,
      "top2": 8,
      "top3": 10,
      "top4": 11,
      "top5": 13,
      "top10": 14,
      "top15": 14,
      "top20": 14
    },
    "russell": {
      "top1": 5,
      "top2": 7,
      "top3": 11,
      "top4": 11,
      "top5": 11,
      "top10": 14,
      "top15": 14,
      "top20": 14
    },
    "turantula": {
      "top1": 6,
      "top2": 8,
      "top3": 10,
      "top4": 10,
      "top5": 11,
      "top10": 14,
      "top15": 14,
      "top20": 14
    },
    "naish1": {
      "top1": 3,
      "top2": 9,
      "top3": 10,
      "top4": 10,
      "top5": 10,
      "top10": 13,
      "top15": 13,
      "top20": 13
    },
    "binary": {
      "top1": 14,
      "top2": 14,
      "top3": 14,
      "top4": 14,
      "top5": 14,
      "top10": 14,
      "top15": 14,
      "top20": 14
    },
    "crosstab": {
      "top1": 6,
      "top2": 10,
      "top3": 11,
      "top4": 13,
      "top5": 13,
      "top10": 13,
      "top15": 13,
      "top20": 13
    }
  },
  "pred_topN_randomForestModel_10.json": {
    "dstar": {
      "top1": 5,
      "top2": 6,
      "top3": 8,
      "top4": 9,
      "top5": 10,
      "top10": 14,
      "top15": 14,
      "top20": 14
    },
    "ochiai": {
      "top1": 5,
      "top2": 7,
      "top3": 10,
      "top4": 10,
      "top5": 10,
      "top10": 14,
      "top15": 14,
      "top20": 14
    },
    "gp13": {
      "top1": 5,
      "top2": 6,
      "top3": 8,
      "top4": 8,
      "top5": 9,
      "top10": 14,
      "top15": 14,
      "top20": 14
    },
    "op2": {
      "top1": 5,
      "top2": 6,
      "top3": 8,
      "top4": 8,
      "top5": 9,
      "top10": 14,
      "top15": 14,
      "top20": 14
    },
    "jaccard": {
      "top1": 5,
      "top2": 7,
      "top3": 10,
      "top4": 10,
      "top5": 10,
      "top10": 14,
      "top15": 14,
      "top20": 14
    },
    "russell": {
      "top1": 6,
      "top2": 7,
      "top3": 10,
      "top4": 10,
      "top5": 10,
      "top10": 14,
      "top15": 14,
      "top20": 14
    },
    "turantula": {
      "top1": 7,
      "top2": 9,
      "top3": 11,
      "top4": 12,
      "top5": 12,
      "top10": 14,
      "top15": 14,
      "top20": 14
    },
    "naish1": {
      "top1": 6,
      "top2": 8,
      "top3": 10,
      "top4": 11,
      "top5": 11,
      "top10": 14,
      "top15": 14,
      "top20": 14
    },
    "binary": {
      "top1": 8,
      "top2": 8,
      "top3": 8,
      "top4": 10,
      "top5": 12,
      "top10": 12,
      "top15": 12,
      "top20": 12
    },
    "crosstab": {
      "top1": 8,
      "top2": 9,
      "top3": 10,
      "top4": 10,
      "top5": 12,
      "top10": 14,
      "top15": 14,
      "top20": 14
    }
  },
  "pred_topN_randomForestModel_1_2.json": {
    "dstar": {
      "top1": 6,
      "top2": 6,
      "top3": 11,
      "top4": 11,
      "top5": 12,
      "top10": 13,
      "top15": 14,
      "top20": 14
    },
    "ochiai": {
      "top1": 7,
      "top2": 7,
      "top3": 11,
      "top4": 11,
      "top5": 13,
      "top10": 13,
      "top15": 14,
      "top20": 14
    },
    "gp13": {
      "top1": 6,
      "top2": 6,
      "top3": 10,
      "top4": 10,
      "top5": 12,
      "top10": 13,
      "top15": 14,
      "top20": 14
    },
    "op2": {
      "top1": 6,
      "top2": 6,
      "top3": 9,
      "top4": 9,
      "top5": 11,
      "top10": 13,
      "top15": 14,
      "top20": 14
    },
    "jaccard": {
      "top1": 7,
      "top2": 7,
      "top3": 11,
      "top4": 12,
      "top5": 13,
      "top10": 13,
      "top15": 14,
      "top20": 14
    },
    "russell": {
      "top1": 6,
      "top2": 6,
      "top3": 10,
      "top4": 10,
      "top5": 13,
      "top10": 13,
      "top15": 14,
      "top20": 14
    },
    "turantula": {
      "top1": 10,
      "top2": 10,
      "top3": 14,
      "top4": 14,
      "top5": 14,
      "top10": 14,
      "top15": 14,
      "top20": 14
    },
    "naish1": {
      "top1": 10,
      "top2": 10,
      "top3": 11,
      "top4": 11,
      "top5": 14,
      "top10": 14,
      "top15": 14,
      "top20": 14
    },
    "binary": {
      "top1": 7,
      "top2": 9,
      "top3": 11,
      "top4": 11,
      "top5": 12,
      "top10": 14,
      "top15": 14,
      "top20": 14
    },
    "crosstab": {
      "top1": 8,
      "top2": 8,
      "top3": 10,
      "top4": 11,
      "top5": 12,
      "top10": 13,
      "top15": 14,
      "top20": 14
    }
  },
  "pred_topN_randomForestModel_2_2.json": {
    "dstar": {
      "top1": 6,
      "top2": 8,
      "top3": 13,
      "top4": 13,
      "top5": 14,
      "top10": 14,
      "top15": 14,
      "top20": 14
    },
    "ochiai": {
      "top1": 10,
      "top2": 11,
      "top3": 13,
      "top4": 13,
      "top5": 14,
      "top10": 14,
      "top15": 14,
      "top20": 14
    },
    "gp13": {
      "top1": 8,
      "top2": 9,
      "top3": 13,
      "top4": 13,
      "top5": 14,
      "top10": 14,
      "top15": 14,
      "top20": 14
    },
    "op2": {
      "top1": 8,
      "top2": 9,
      "top3": 13,
      "top4": 13,
      "top5": 14,
      "top10": 14,
      "top15": 14,
      "top20": 14
    },
    "jaccard": {
      "top1": 8,
      "top2": 9,
      "top3": 13,
      "top4": 13,
      "top5": 14,
      "top10": 14,
      "top15": 14,
      "top20": 14
    },
    "russell": {
      "top1": 8,
      "top2": 9,
      "top3": 14,
      "top4": 14,
      "top5": 14,
      "top10": 14,
      "top15": 14,
      "top20": 14
    },
    "turantula": {
      "top1": 10,
      "top2": 12,
      "top3": 13,
      "top4": 13,
      "top5": 14,
      "top10": 14,
      "top15": 14,
      "top20": 14
    },
    "naish1": {
      "top1": 13,
      "top2": 13,
      "top3": 14,
      "top4": 14,
      "top5": 14,
      "top10": 14,
      "top15": 14,
      "top20": 14
    },
    "binary": {
      "top1": 5,
      "top2": 5,
      "top3": 8,
      "top4": 8,
      "top5": 8,
      "top10": 11,
      "top15": 14,
      "top20": 14
    },
    "crosstab": {
      "top1": 11,
      "top2": 12,
      "top3": 13,
      "top4": 13,
      "top5": 14,
      "top10": 14,
      "top15": 14,
      "top20": 14
    }
  },
  "pred_topN_randomForestModel_3_2.json": {
    "dstar": {
      "top1": 7,
      "top2": 10,
      "top3": 11,
      "top4": 12,
      "top5": 12,
      "top10": 13,
      "top15": 14,
      "top20": 14
    },
    "ochiai": {
      "top1": 10,
      "top2": 11,
      "top3": 11,
      "top4": 12,
      "top5": 13,
      "top10": 13,
      "top15": 14,
      "top20": 14
    },
    "gp13": {
      "top1": 8,
      "top2": 10,
      "top3": 10,
      "top4": 12,
      "top5": 12,
      "top10": 13,
      "top15": 14,
      "top20": 14
    },
    "op2": {
      "top1": 8,
      "top2": 10,
      "top3": 10,
      "top4": 12,
      "top5": 12,
      "top10": 13,
      "top15": 14,
      "top20": 14
    },
    "jaccard": {
      "top1": 10,
      "top2": 11,
      "top3": 12,
      "top4": 12,
      "top5": 13,
      "top10": 13,
      "top15": 14,
      "top20": 14
    },
    "russell": {
      "top1": 9,
      "top2": 11,
      "top3": 11,
      "top4": 12,
      "top5": 12,
      "top10": 13,
      "top15": 14,
      "top20": 14
    },
    "turantula": {
      "top1": 8,
      "top2": 13,
      "top3": 13,
      "top4": 13,
      "top5": 13,
      "top10": 13,
      "top15": 14,
      "top20": 14
    },
    "naish1": {
      "top1": 8,
      "top2": 10,
      "top3": 13,
      "top4": 14,
      "top5": 14,
      "top10": 14,
      "top15": 14,
      "top20": 14
    },
    "binary": {
      "top1": 9,
      "top2": 9,
      "top3": 9,
      "top4": 11,
      "top5": 11,
      "top10": 13,
      "top15": 13,
      "top20": 14
    },
    "crosstab": {
      "top1": 11,
      "top2": 11,
      "top3": 12,
      "top4": 12,
      "top5": 13,
      "top10": 13,
      "top15": 14,
      "top20": 14
    }
  },
  "pred_topN_randomForestModel_4_2.json": {
    "dstar": {
      "top1": 5,
      "top2": 6,
      "top3": 10,
      "top4": 11,
      "top5": 12,
      "top10": 14,
      "top15": 14,
      "top20": 14
    },
    "ochiai": {
      "top1": 6,
      "top2": 7,
      "top3": 10,
      "top4": 11,
      "top5": 11,
      "top10": 14,
      "top15": 14,
      "top20": 14
    },
    "gp13": {
      "top1": 5,
      "top2": 7,
      "top3": 11,
      "top4": 12,
      "top5": 12,
      "top10": 14,
      "top15": 14,
      "top20": 14
    },
    "op2": {
      "top1": 5,
      "top2": 8,
      "top3": 11,
      "top4": 12,
      "top5": 12,
      "top10": 14,
      "top15": 14,
      "top20": 14
    },
    "jaccard": {
      "top1": 6,
      "top2": 7,
      "top3": 10,
      "top4": 11,
      "top5": 11,
      "top10": 14,
      "top15": 14,
      "top20": 14
    },
    "russell": {
      "top1": 8,
      "top2": 11,
      "top3": 11,
      "top4": 12,
      "top5": 12,
      "top10": 14,
      "top15": 14,
      "top20": 14
    },
    "turantula": {
      "top1": 7,
      "top2": 11,
      "top3": 14,
      "top4": 14,
      "top5": 14,
      "top10": 14,
      "top15": 14,
      "top20": 14
    },
    "naish1": {
      "top1": 9,
      "top2": 9,
      "top3": 11,
      "top4": 12,
      "top5": 12,
      "top10": 14,
      "top15": 14,
      "top20": 14
    },
    "binary": {
      "top1": 9,
      "top2": 9,
      "top3": 9,
      "top4": 12,
      "top5": 12,
      "top10": 12,
      "top15": 12,
      "top20": 14
    },
    "crosstab": {
      "top1": 8,
      "top2": 9,
      "top3": 10,
      "top4": 11,
      "top5": 11,
      "top10": 14,
      "top15": 14,
      "top20": 14
    }
  },
  "pred_topN_randomForestModel_5_2.json": {
    "dstar": {
      "top1": 6,
      "top2": 7,
      "top3": 9,
      "top4": 11,
      "top5": 11,
      "top10": 14,
      "top15": 14,
      "top20": 14
    },
    "ochiai": {
      "top1": 6,
      "top2": 9,
      "top3": 11,
      "top4": 12,
      "top5": 12,
      "top10": 14,
      "top15": 14,
      "top20": 14
    },
    "gp13": {
      "top1": 5,
      "top2": 7,
      "top3": 9,
      "top4": 11,
      "top5": 11,
      "top10": 14,
      "top15": 14,
      "top20": 14
    },
    "op2": {
      "top1": 5,
      "top2": 7,
      "top3": 9,
      "top4": 11,
      "top5": 11,
      "top10": 14,
      "top15": 14,
      "top20": 14
    },
    "jaccard": {
      "top1": 7,
      "top2": 9,
      "top3": 11,
      "top4": 12,
      "top5": 12,
      "top10": 14,
      "top15": 14,
      "top20": 14
    },
    "russell": {
      "top1": 7,
      "top2": 9,
      "top3": 11,
      "top4": 12,
      "top5": 12,
      "top10": 14,
      "top15": 14,
      "top20": 14
    },
    "turantula": {
      "top1": 8,
      "top2": 10,
      "top3": 12,
      "top4": 14,
      "top5": 14,
      "top10": 14,
      "top15": 14,
      "top20": 14
    },
    "naish1": {
      "top1": 5,
      "top2": 9,
      "top3": 10,
      "top4": 11,
      "top5": 12,
      "top10": 14,
      "top15": 14,
      "top20": 14
    },
    "binary": {
      "top1": 10,
      "top2": 10,
      "top3": 10,
      "top4": 12,
      "top5": 14,
      "top10": 14,
      "top15": 14,
      "top20": 14
    },
    "crosstab": {
      "top1": 10,
      "top2": 10,
      "top3": 11,
      "top4": 12,
      "top5": 12,
      "top10": 14,
      "top15": 14,
      "top20": 14
    }
  }
}